{
  "title": "2019-49",
  "visible": true,
  "image": "/images/uploads/Frost Reflexe.JPG",
  "image_name": "Frost Reflexe",
  "image_description": "Der Apfelbaum im Goldsteintal hatte es mir sofort angetan. Übersät von Eiskristallen stand er da und der Sonnenstrahl fiel über den Berg direkt in die Zweige. Es handelt sich übrigens um ein Farbfoto. Und ich musste ein paar Belichtungseinstellungen ausprobieren um den gewünschten Effekt zu erzielen.",
  "photos": [
    {
      "image": "/images/uploads/Dom in Rot.JPG",
      "day": "Mo",
      "description": "Dom in Rot\nDer Mainzer Dom befindet sich rechts in der Mitte. Seine Kuppel ragt in die Eisenbahnbrücke hinein, die über den Rhein führt. Das Bergmassiv zentral hinter der letzten Nebelwand ist der Donnersberg. Er ist Luftlinie ca. 60 km weit entfernt. Nur die Blende schloss ich bewusst ein Stück um die Schärfe-Ebene zu vergrößern."
    }
  ]
}