{
  "title": "2019-06",
  "visible": true,
  "image": "/images/uploads/miniatur.jpg",
  "image_name": "Porta Micra",
  "image_description": "Auf dem Rückweg aus dem Saarland hielt ich in Trier und natürlich musste ich die Porta Nigra einfangen.\n \nDas kleine Modell davon steht normalerweise im Schlagschatten des dunklen Tores.\nAber diesmal spiegelte sich ein Lichtstrahl im Fenster auf der anderen Straßenseite und hellte die Miniatur auf.\nMan erkennt deshalb auf der dunklen Original-Mauer rechts einen hell beschienenen Fleck, obwohl die Sonne auf der anderen Seite des Tores steht !\n \nDen reflektierten Sonnenstrahl empfand ich als Aufforderung um das Modell als Hauptmotiv einzurichten.",
  "photos": [
    {
      "image": "/images/uploads/028-vereinte-kräfte.jpg",
      "day": "So",
      "description": "Arbeitseinsatz auf dem Heimgelände."
    }
  ]
}